[
  {
    "courseId": "course-mathematics-101",
    "title": "Toán Học Cơ Bản Lớp 10",
    "description": "Khóa học này cung cấp cho học sinh kiến thức toán học cơ bản dành cho lớp 10, bao gồm đại số, hình học và lượng giác.",
    "category": "toan-hoc",
    "teacherId": "teacher-123",
    "teacherName": "Nguyễn Văn A",
    "status": "Published",
    "level": "Intermediate",
    "image": "https://images.unsplash.com/photo-1635070041078-e363dbe005cb?w=800&auto=format&fit=crop",
    "meetLink": "abc-defg-hij",
    "sections": [
      {
        "sectionId": "section-algebra",
        "sectionTitle": "Đại Số",
        "sectionDescription": "Các khái niệm cơ bản về đại số và phương trình",
        "chapters": [
          {
            "chapterId": "chapter-algebra-intro",
            "type": "Text",
            "title": "Giới thiệu về Đại số",
            "content": "<p>Đại số là một nhánh của toán học nghiên cứu về các ký hiệu và các quy tắc để thao tác với các ký hiệu đó. Trong đại số, các chữ cái và các ký hiệu khác thường được sử dụng để biểu diễn các số và khối lượng.</p><h2>Nội dung chính</h2><ul><li>Khái niệm cơ bản</li><li>Biểu thức đại số</li><li>Phép tính đại số</li></ul>",
            "video": "https://example.com/videos/algebra-intro.mp4"
          },
          {
            "chapterId": "chapter-equations",
            "type": "Text",
            "title": "Phương trình bậc nhất",
            "content": "<p>Phương trình bậc nhất là phương trình có dạng ax + b = 0, trong đó a và b là các hằng số, a ≠ 0, và x là biến số. Giải phương trình bậc nhất là tìm các giá trị của x thỏa mãn phương trình.</p><h2>Các bước giải</h2><ol><li>Chuyển vế để đưa về dạng ax = -b</li><li>Chia hai vế cho a để được x = -b/a</li></ol>",
            "video": "https://example.com/videos/equations-101.mp4"
          }
        ]
      },
      {
        "sectionId": "section-geometry",
        "sectionTitle": "Hình Học",
        "sectionDescription": "Khái niệm về không gian và các hình học cơ bản",
        "chapters": [
          {
            "chapterId": "chapter-geometry-intro",
            "type": "Text",
            "title": "Giới thiệu về Hình học",
            "content": "<p>Hình học là nhánh của toán học nghiên cứu về các hình dạng, kích thước, vị trí tương đối của các hình và tính chất của không gian.</p><h2>Các chủ đề chính</h2><ul><li>Điểm, đường thẳng, mặt phẳng</li><li>Các góc và quan hệ</li><li>Tam giác và đa giác</li></ul>",
            "video": "https://example.com/videos/geometry-intro.mp4"
          },
          {
            "chapterId": "chapter-triangles",
            "type": "Text",
            "title": "Tam giác và tính chất",
            "content": "<p>Tam giác là một đa giác có ba cạnh và ba góc. Tổng ba góc trong tam giác bằng 180 độ.</p><h2>Các loại tam giác</h2><ul><li>Tam giác đều: ba cạnh bằng nhau</li><li>Tam giác cân: hai cạnh bằng nhau</li><li>Tam giác vuông: có một góc 90 độ</li></ul>",
            "video": "https://example.com/videos/triangles.mp4"
          }
        ]
      }
    ]
  },
  {
    "courseId": "course-literature-101",
    "title": "Ngữ Văn Lớp 10",
    "description": "Khóa học này giới thiệu các tác phẩm văn học Việt Nam và thế giới quan trọng trong chương trình lớp 10.",
    "category": "ngu-van",
    "teacherId": "teacher-456",
    "teacherName": "Trần Thị B",
    "status": "Published",
    "level": "Beginner",
    "image": "https://images.unsplash.com/photo-1550399105-c4db5fb85c18?w=800&auto=format&fit=crop",
    "sections": [
      {
        "sectionId": "section-vietnamese-lit",
        "sectionTitle": "Văn học Việt Nam",
        "sectionDescription": "Các tác phẩm văn học Việt Nam tiêu biểu",
        "chapters": [
          {
            "chapterId": "chapter-truyen-kieu",
            "type": "Text",
            "title": "Truyện Kiều - Nguyễn Du",
            "content": "<p>Truyện Kiều là một kiệt tác văn học của Nguyễn Du, được sáng tác vào đầu thế kỷ 19. Tác phẩm kể về cuộc đời đầy biến cố của nàng Kiều.</p><h2>Giá trị nghệ thuật</h2><ul><li>Ngôn ngữ tinh tế</li><li>Miêu tả tâm lý nhân vật sâu sắc</li><li>Phản ánh xã hội phong kiến</li></ul>",
            "video": "https://example.com/videos/truyen-kieu.mp4"
          },
          {
            "chapterId": "chapter-tay-tien",
            "type": "Text",
            "title": "Tây Tiến - Quang Dũng",
            "content": "<p>Tây Tiến là bài thơ nổi tiếng của nhà thơ Quang Dũng, viết về đoàn quân Tây Tiến trong kháng chiến chống Pháp.</p><h2>Phân tích</h2><ul><li>Hình ảnh người lính</li><li>Vẻ đẹp thiên nhiên miền Tây</li><li>Tinh thần yêu nước</li></ul>",
            "video": "https://example.com/videos/tay-tien.mp4"
          }
        ]
      },
      {
        "sectionId": "section-world-lit",
        "sectionTitle": "Văn học Thế giới",
        "sectionDescription": "Các tác phẩm văn học thế giới tiêu biểu",
        "chapters": [
          {
            "chapterId": "chapter-hamlet",
            "type": "Text",
            "title": "Hamlet - William Shakespeare",
            "content": "<p>Hamlet là một vở bi kịch nổi tiếng của William Shakespeare, kể về hoàng tử Hamlet của Đan Mạch và cuộc báo thù của ông cho cái chết của cha mình.</p><h2>Chủ đề chính</h2><ul><li>Sự phản bội</li><li>Báo thù</li><li>Cái chết và sự điên loạn</li></ul>",
            "video": "https://example.com/videos/hamlet.mp4"
          }
        ]
      }
    ]
  },
  {
    "courseId": "course-physics-101",
    "title": "Vật Lý Cơ Bản Lớp 10",
    "description": "Khóa học này giới thiệu các nguyên lý cơ bản về cơ học, nhiệt học và điện học theo chương trình lớp 10.",
    "category": "vat-ly",
    "teacherId": "teacher-789",
    "teacherName": "Lê Văn C",
    "status": "Published",
    "level": "Intermediate",
    "image": "https://images.unsplash.com/photo-1636466497217-26a8cbeaf0aa?w=800&auto=format&fit=crop",
    "meetLink": "xyz-abcd-efg",
    "sections": [
      {
        "sectionId": "section-mechanics",
        "sectionTitle": "Cơ Học",
        "sectionDescription": "Các khái niệm và nguyên lý cơ bản về chuyển động và lực",
        "chapters": [
          {
            "chapterId": "chapter-kinematics",
            "type": "Text",
            "title": "Động học",
            "content": "<p>Động học là phần của cơ học nghiên cứu chuyển động của vật thể mà không xét đến nguyên nhân gây ra chuyển động đó.</p><h2>Các khái niệm cơ bản</h2><ul><li>Vận tốc</li><li>Gia tốc</li><li>Chuyển động đều và biến đổi đều</li></ul>",
            "video": "https://example.com/videos/kinematics.mp4"
          },
          {
            "chapterId": "chapter-newton-laws",
            "type": "Text",
            "title": "Các định luật Newton",
            "content": "<p>Các định luật Newton về chuyển động là ba định luật vật lý mô tả mối quan hệ giữa chuyển động của một vật và các lực tác dụng lên nó.</p><h2>Ba định luật</h2><ol><li>Định luật quán tính</li><li>Định luật về lực và gia tốc</li><li>Định luật tác dụng và phản tác dụng</li></ol>",
            "video": "https://example.com/videos/newton-laws.mp4"
          }
        ]
      },
      {
        "sectionId": "section-thermodynamics",
        "sectionTitle": "Nhiệt Học",
        "sectionDescription": "Các khái niệm về nhiệt và các quá trình nhiệt động học",
        "chapters": [
          {
            "chapterId": "chapter-temperature",
            "type": "Text",
            "title": "Nhiệt độ và sự giãn nở nhiệt",
            "content": "<p>Nhiệt độ là đại lượng vật lý đặc trưng cho mức độ nóng lạnh của vật. Khi nhiệt độ tăng, hầu hết các vật sẽ giãn nở.</p><h2>Các vấn đề chính</h2><ul><li>Thang nhiệt độ</li><li>Sự giãn nở của chất rắn, lỏng, khí</li><li>Ứng dụng thực tế</li></ul>",
            "video": "https://example.com/videos/temperature.mp4"
          }
        ]
      }
    ]
  },
  {
    "courseId": "course-chemistry-101",
    "title": "Hóa Học Lớp 10",
    "description": "Khóa học cung cấp kiến thức cơ bản về nguyên tử, phân tử, và các phản ứng hóa học theo chương trình lớp 10.",
    "category": "hoa-hoc",
    "teacherId": "teacher-101",
    "teacherName": "Phạm Thị D",
    "status": "Published",
    "level": "Intermediate",
    "image": "https://images.unsplash.com/photo-1603126857599-f6e157fa2fe6?w=800&auto=format&fit=crop",
    "sections": [
      {
        "sectionId": "section-atomic-structure",
        "sectionTitle": "Cấu trúc nguyên tử",
        "sectionDescription": "Tìm hiểu về cấu trúc và thành phần của nguyên tử",
        "chapters": [
          {
            "chapterId": "chapter-atomic-models",
            "type": "Text",
            "title": "Các mô hình nguyên tử",
            "content": "<p>Mô hình nguyên tử mô tả cấu trúc của nguyên tử dựa trên các lý thuyết và thực nghiệm khoa học.</p><h2>Các mô hình chính</h2><ul><li>Mô hình Dalton</li><li>Mô hình Thomson</li><li>Mô hình Rutherford</li><li>Mô hình Bohr</li></ul>",
            "video": "https://example.com/videos/atomic-models.mp4"
          },
          {
            "chapterId": "chapter-periodic-table",
            "type": "Text",
            "title": "Bảng tuần hoàn các nguyên tố hóa học",
            "content": "<p>Bảng tuần hoàn là một sự sắp xếp có hệ thống các nguyên tố hóa học, được tổ chức dựa trên cấu trúc điện tử của chúng.</p><h2>Các nhóm và chu kỳ</h2><ul><li>Nhóm A và nhóm B</li><li>Các kim loại và phi kim</li><li>Xu hướng trong bảng tuần hoàn</li></ul>",
            "video": "https://example.com/videos/periodic-table.mp4"
          }
        ]
      },
      {
        "sectionId": "section-chemical-bonds",
        "sectionTitle": "Liên kết hóa học",
        "sectionDescription": "Các loại liên kết giữa các nguyên tử trong phân tử",
        "chapters": [
          {
            "chapterId": "chapter-covalent-bonds",
            "type": "Text",
            "title": "Liên kết cộng hóa trị",
            "content": "<p>Liên kết cộng hóa trị là liên kết hóa học được hình thành khi các nguyên tử chia sẻ electron với nhau.</p><h2>Các loại liên kết cộng hóa trị</h2><ul><li>Liên kết đơn</li><li>Liên kết đôi</li><li>Liên kết ba</li></ul>",
            "video": "https://example.com/videos/covalent-bonds.mp4"
          }
        ]
      }
    ]
  },
  {
    "courseId": "course-biology-101",
    "title": "Sinh Học Lớp 10",
    "description": "Khóa học cung cấp kiến thức về tế bào, di truyền và sinh thái học theo chương trình lớp 10.",
    "category": "sinh-hoc",
    "teacherId": "teacher-202",
    "teacherName": "Hoàng Văn E",
    "status": "Published",
    "level": "Beginner",
    "image": "https://images.unsplash.com/photo-1627563859026-1f792382671c?w=800&auto=format&fit=crop",
    "sections": [
      {
        "sectionId": "section-cell-biology",
        "sectionTitle": "Sinh học tế bào",
        "sectionDescription": "Cấu trúc và chức năng của tế bào sinh vật",
        "chapters": [
          {
            "chapterId": "chapter-cell-structure",
            "type": "Text",
            "title": "Cấu trúc tế bào",
            "content": "<p>Tế bào là đơn vị cấu trúc và chức năng cơ bản của tất cả các sinh vật. Có hai loại tế bào chính: tế bào nhân sơ và tế bào nhân thật.</p><h2>Các bộ phận của tế bào nhân thật</h2><ul><li>Màng tế bào</li><li>Tế bào chất</li><li>Nhân tế bào</li><li>Các bào quan</li></ul>",
            "video": "https://example.com/videos/cell-structure.mp4"
          },
          {
            "chapterId": "chapter-cell-division",
            "type": "Text",
            "title": "Phân bào",
            "content": "<p>Phân bào là quá trình tế bào nhân đôi thành hai tế bào con. Có hai loại phân bào chính: nguyên phân và giảm phân.</p><h2>Các giai đoạn của nguyên phân</h2><ol><li>Kỳ đầu</li><li>Kỳ giữa</li><li>Kỳ sau</li><li>Kỳ cuối</li></ol>",
            "video": "https://example.com/videos/cell-division.mp4"
          }
        ]
      }
    ]
  }
]
